pegg/.DS_Store
pegg/RF_PE.pkl
pegg/V3_model_full.pickle
pegg/V3_model_nopos.pickle
pegg/__init__.py
pegg/base.py
pegg/crispor_azimuth.py
pegg/human_safe_regions_bassik.csv
pegg/library.py
pegg/mouse_safe_regions_bassik.csv
pegg/non_targeting_human_base.csv
pegg/non_targeting_human_prime.csv
pegg/non_targeting_unformatted_hum.txt
pegg/non_targeting_unformatted_mus.txt
pegg/prime.py
pegg/__pycache__/__init__.cpython-39.pyc
pegg/__pycache__/base.cpython-39.pyc
pegg/__pycache__/crispor_azimuth.cpython-39.pyc
pegg/__pycache__/library.cpython-39.pyc
pegg/__pycache__/prime.cpython-39.pyc
pegg-2.1.0.dist-info/LICENSE
pegg-2.1.0.dist-info/METADATA
pegg-2.1.0.dist-info/WHEEL
pegg-2.1.0.dist-info/top_level.txt
pegg-2.1.0.dist-info/RECORD
